pystack.py
pystack_manager-0.9.4.dist-info/LICENSE.txt
pystack_manager-0.9.4.dist-info/METADATA
pystack_manager-0.9.4.dist-info/WHEEL
pystack_manager-0.9.4.dist-info/top_level.txt
pystack_manager-0.9.4.dist-info/RECORD
