Metadata-Version: 2.1
Name: pystack-manager
Version: 0.9.4
Summary: python stack manager
Home-page: UNKNOWN
Author: Plydow
Maintainer: Plydow
Maintainer-email: plydow.contact@gmail.com
License: GNU GPLv3
Keywords: stack pystack
Platform: ALL
Classifier: Development Status :: 5 - Production/Stable
Classifier: Topic :: Education
Classifier: Programming Language :: Python :: 3
Classifier: License :: OSI Approved :: GNU General Public License v3 (GPLv3)
Classifier: Operating System :: OS Independent
Requires-Python: >=3
